finlab_sentinel/__init__.py
finlab_sentinel/exceptions.py
finlab_sentinel/py.typed
finlab_sentinel/cli/__init__.py
finlab_sentinel/cli/main.py
finlab_sentinel/comparison/__init__.py
finlab_sentinel/comparison/differ.py
finlab_sentinel/comparison/hasher.py
finlab_sentinel/comparison/policies.py
finlab_sentinel/comparison/report.py
finlab_sentinel/config/__init__.py
finlab_sentinel/config/loader.py
finlab_sentinel/config/schema.py
finlab_sentinel/core/__init__.py
finlab_sentinel/core/hooks.py
finlab_sentinel/core/interceptor.py
finlab_sentinel/core/patcher.py
finlab_sentinel/core/registry.py
finlab_sentinel/core/time_travel.py
finlab_sentinel/handlers/__init__.py
finlab_sentinel/handlers/base.py
finlab_sentinel/handlers/callback.py
finlab_sentinel/handlers/exception.py
finlab_sentinel/handlers/warning.py
finlab_sentinel/storage/__init__.py
finlab_sentinel/storage/backend.py
finlab_sentinel/storage/cleanup.py
finlab_sentinel/storage/index.py
finlab_sentinel/storage/parquet.py
finlab_sentinel-0.1.7.dist-info/METADATA
finlab_sentinel-0.1.7.dist-info/WHEEL
finlab_sentinel-0.1.7.dist-info/entry_points.txt
finlab_sentinel-0.1.7.dist-info/RECORD
